text_content_generator/__init__.py
text_content_generator/audio.py
text_content_generator/generate.py
text_content_generator/pdf.py
text_content_generator/summarize.py
text_content_generator/webpage.py
text_content_generator/youtube.py
text_content_generator-0.0.3.dist-info/LICENSE
text_content_generator-0.0.3.dist-info/METADATA
text_content_generator-0.0.3.dist-info/WHEEL
text_content_generator-0.0.3.dist-info/top_level.txt
text_content_generator-0.0.3.dist-info/RECORD
