Metadata-Version: 2.1
Name: text-content-generator
Version: 0.0.3
Summary: To scrape or collect text based content from media
Author-email: mheshze <assassinmahesh@gmail.com>
Project-URL: Homepage, https://github.com/mheshze/TextContentGeneration.git
Classifier: Programming Language :: Python :: 3
Classifier: License :: OSI Approved :: MIT License
Classifier: Operating System :: OS Independent
Requires-Python: >=3.9
License-File: LICENSE
